README.md
setup.py
confuse_jinja/__init__.py
confuse_jinja/safe_eval.py
confuse_jinja/util.py
confuse_jinja.egg-info/PKG-INFO
confuse_jinja.egg-info/SOURCES.txt
confuse_jinja.egg-info/dependency_links.txt
confuse_jinja.egg-info/requires.txt
confuse_jinja.egg-info/top_level.txt