Metadata-Version: 2.1
Name: confuse-jinja
Version: 0.0.1
Summary: UNKNOWN
Home-page: https://github.com/beasteers/confuse_jinja
Author: Bea Steers
Author-email: bea.steers@gmail.com
License: MIT License
Platform: UNKNOWN
